{"number_of_pages": 262, "weight": "12 ounces", "covers": [866134], "ia_loaded_id": ["overcomingspirit00gill"], "latest_revision": 11, "ocaid": "overcomingspirit00gill", "isbn_13": ["9781591856078"], "source_records": ["amazon:1591856078:ft:3912638926:184272", "marc:marc_loc_updates/v37.i04.records.utf8:2413659:704", "marc:marc_loc_updates/v37.i10.records.utf8:4795222:730", "ia:overcomingspirit00gill"], "title": "Overcoming Spiritual Blindness", "languages": [{"key": "/languages/eng"}], "subjects": ["Religion - Christian Living", "Religion - Inspirational/Spirituality", "Religion", "Christian Life - Character & Values", "Spirituality - General", "Christian Life - General", "Christianity - Christian Life - Character & Values"], "oclc_numbers": ["70669273"], "type": {"key": "/type/edition"}, "physical_dimensions": "8.3 x 5.5 x 1 inches", "revision": 11, "publishers": ["Creation House"], "ia_box_id": ["IA129801"], "physical_format": "Paperback", "last_modified": {"type": "/type/datetime", "value": "2012-08-17T10:23:17.600124"}, "key": "/books/OL8858327M", "authors": [{"key": "/authors/OL1481082A"}], "created": {"type": "/type/datetime", "value": "2008-04-30T09:38:13.731961"}, "identifiers": {"goodreads": ["138140"], "librarything": ["2358235"]}, "first_sentence": {"type": "/type/text", "value": "IN THIS FIRST section (Chapters 1-8), I would like to show you a very important reality of faith: the need all have for progressing from superficial, external, religious traditions to a satisfying experience of living faith."}, "isbn_10": ["1591856078"], "publish_date": "August 23, 2005", "works": [{"key": "/works/OL5965734W"}]}