{"number_of_pages": 376, "subtitle": "a novel", "covers": [6740926], "lc_classifications": ["PS3554.I367 N37 2007"], "latest_revision": 14, "ocaid": "napoleonspyramid00diet", "edition_name": "1st ed.", "genres": ["Fiction."], "source_records": ["marc:marc_loc_updates/v35.i23.records.utf8:10103363:729", "marc:marc_loc_updates/v35.i21.records.utf8:15401694:717", "marc:marc_loc_updates/v35.i24.records.utf8:9832018:729", "marc:marc_loc_updates/v37.i04.records.utf8:2963924:790", "marc:CollingswoodLibraryMarcDump10-27-2008/Collingswood.out:72643833:1838", "ia:napoleonspyramid00diet", "ia:napoleonspyramid00diet"], "title": "Napoleon's pyramids", "languages": [{"key": "/languages/eng"}], "subjects": ["Great Pyramid (Egypt) -- Fiction", "Egypt -- History -- French occupation, 1798-1801 -- Fiction"], "publish_country": "nyu", "by_statement": "William Dietrich.", "type": {"key": "/type/edition"}, "revision": 14, "publishers": ["HarperCollins Pub."], "ia_box_id": ["IA132118"], "last_modified": {"type": "/type/datetime", "value": "2011-08-12T04:26:54.606027"}, "key": "/books/OL17951513M", "authors": [{"key": "/authors/OL22399A"}], "publish_places": ["New York"], "pagination": "376 p. ;", "created": {"type": "/type/datetime", "value": "2008-10-08T15:45:59.958978"}, "dewey_decimal_class": ["813/.54"], "identifiers": {"librarything": ["1743559"], "goodreads": ["189568"]}, "lccn": ["2006041247"], "isbn_10": ["0060848324"], "publish_date": "2007", "works": [{"key": "/works/OL14920946W"}]}