{"series": ["Diseases & disorders"], "lc_classifications": ["QR406 .N37 2007"], "latest_revision": 11, "ocaid": "humanpapillomavi00nard", "genres": ["Juvenile literature."], "source_records": ["marc:marc_loc_updates/v35.i17.records.utf8:11710899:650", "marc:marc_loc_updates/v35.i18.records.utf8:12146785:657", "marc:marc_loc_updates/v35.i23.records.utf8:15450016:752", "marc:marc_loc_updates/v36.i06.records.utf8:8751249:1033", "marc:marc_loc_updates/v37.i04.records.utf8:3488760:1033", "ia:humanpapillomavi00nard"], "title": "Human papillomavirus (HPV)", "languages": [{"key": "/languages/eng"}], "subjects": ["Papillomaviruses -- Juvenile literature"], "publish_country": "miu", "by_statement": "by Don Nardo.", "oclc_numbers": ["123285023"], "type": {"key": "/type/edition"}, "revision": 11, "publishers": ["Lucent Books"], "last_modified": {"type": "/type/datetime", "value": "2014-07-30T11:57:26.322798"}, "key": "/books/OL17900994M", "authors": [{"key": "/authors/OL19822A"}], "publish_places": ["Detroit"], "pagination": "p. cm.", "created": {"type": "/type/datetime", "value": "2008-10-07T10:55:41.063153"}, "dewey_decimal_class": ["616.9/11"], "notes": {"type": "/type/text", "value": "Includes bibliographical references and index."}, "identifiers": {"librarything": ["4986770"], "goodreads": ["2610121"]}, "isbn_13": ["9781590189986"], "lccn": ["2007015827"], "publish_date": "2007", "works": [{"key": "/works/OL15072254W"}]}