{"subtitle": "ein Beitrag zum Versta\u0308ndnis soldatischer Identita\u0308t in den 90er Jahren", "series": ["Berichte / Sozialwissenschaftliches Institut der Bundeswehr,", "Kurzfassung Heft 61", "Berichte (Sozialwissenschaftliches Institut der Bundeswehr) ;", "Kurzfassung Heft 61."], "lc_classifications": ["U22 .S437 1994"], "latest_revision": 3, "source_records": ["marc:marc_records_scriblio_net/part25.dat:115857056:907", "marc:marc_loc_updates/v37.i04.records.utf8:1536596:910"], "title": "Disziplin, Wertewandel, Subjektivita\u0308t", "languages": [{"key": "/languages/ger"}], "subjects": ["Military ethics", "Military discipline"], "publish_country": "gw ", "by_statement": "Ruth Seifert.", "type": {"key": "/type/edition"}, "revision": 3, "publishers": ["Sozialwissenschaftliches Institut der Bundeswehr"], "last_modified": {"type": "/type/datetime", "value": "2009-12-11T23:31:39.237251"}, "key": "/books/OL909699M", "authors": [{"key": "/authors/OL503077A"}], "publish_places": ["Mu\u0308nchen"], "pagination": "iii, 154 p. ;", "created": {"type": "/type/datetime", "value": "2008-04-01T03:28:50.625462"}, "lccn": ["95204520"], "notes": {"type": "/type/text", "value": "Includes bibliographical references (p. 151-154)."}, "number_of_pages": 154, "publish_date": "1994", "works": [{"key": "/works/OL3157500W"}]}