{"subject_place": ["United States."], "lc_classifications": ["L111 .A6 1957, no. 20"], "latest_revision": 5, "source_records": ["marc:marc_records_scriblio_net/part28.dat:187775462:809", "marc:marc_loc_updates/v37.i04.records.utf8:10140544:840", "marc:marc_loc_updates/v40.i24.records.utf8:14511065:1051"], "title": "Local school construction programs.", "languages": [{"key": "/languages/eng"}], "subjects": ["School buildings -- United States"], "publish_country": "dcu", "series": ["United States. Office of Education. Bulletin,", "1957, no. 20", "Bulletin (United States. Office of Education) ;", "1957, no. 20."], "oclc_numbers": ["3859857"], "type": {"key": "/type/edition"}, "revision": 5, "publishers": ["U.S. Dept. of Health, Education, and Welfare, Office of Education"], "last_modified": {"type": "/type/datetime", "value": "2012-06-14T09:49:22.098086"}, "key": "/books/OL248559M", "authors": [{"key": "/authors/OL164174A"}], "publish_places": ["[Washington]"], "pagination": "viii, 80 p.", "created": {"type": "/type/datetime", "value": "2008-04-01T03:28:50.625462"}, "dewey_decimal_class": ["371.62"], "number_of_pages": 80, "lccn": ["e  57000039"], "publish_date": "1957", "works": [{"key": "/works/OL1544061W"}]}