{"identifiers": {"goodreads": ["738994"], "librarything": ["1571268"]}, "weight": "2 pounds", "covers": [542193], "latest_revision": 8, "edition_name": "3rd edition", "source_records": ["amazon:0786425628:cy:2183324900:171084", "marc:marc_loc_updates/v37.i04.records.utf8:2888898:1456"], "title": "African States And Rulers", "languages": [{"key": "/languages/eng"}], "subjects": ["Constitution: government & the state", "21st century", "Government - General", "Africa - History", "Geopolitics", "History", "History - General History", "Kings and rulers", "History: World", "Africa", "Africa - General", "Biography", "Dictionaries", "Politics and government"], "type": {"key": "/type/edition"}, "physical_dimensions": "10.1 x 7 x 1.1 inches", "revision": 8, "publishers": ["McFarland & Company, Inc., Publishers"], "physical_format": "Hardcover", "last_modified": {"type": "/type/datetime", "value": "2010-08-09T21:25:36.773335"}, "key": "/books/OL8139473M", "authors": [{"key": "/authors/OL591909A"}], "created": {"type": "/type/datetime", "value": "2008-04-29T15:03:11.581851"}, "number_of_pages": 431, "isbn_13": ["9780786425624"], "isbn_10": ["0786425628"], "publish_date": "May 4, 2006", "works": [{"key": "/works/OL3531492W"}]}