{"number_of_pages": 424, "covers": [2230187], "latest_revision": 10, "ocaid": "quantummechanics00schw", "contributions": ["R. Kates (Translator)"], "edition_name": "4th ed. edition", "source_records": ["amazon:3540719326:2-aa:4381978460:186774", "marc:marc_loc_updates/v37.i04.records.utf8:4348731:849", "marc:marc_loc_updates/v36.i41.records.utf8:5450683:787", "ia:quantummechanics00schw"], "title": "Quantum Mechanics", "languages": [{"key": "/languages/eng"}], "subjects": ["Quantum physics (quantum mechanics)", "Science", "Science/Mathematics", "Chemistry - Physical & Theoretical", "Physics", "Quantum mechanics", "Science / Quantum Theory", "Quantum Theory"], "type": {"key": "/type/edition"}, "revision": 10, "publishers": ["Springer"], "physical_format": "Hardcover", "last_modified": {"type": "/type/datetime", "value": "2014-07-28T19:41:21.734101"}, "key": "/books/OL9323098M", "authors": [{"key": "/authors/OL20869A"}], "created": {"type": "/type/datetime", "value": "2008-04-30T09:38:13.731961"}, "identifiers": {"librarything": ["1228743"], "goodreads": ["4554803"]}, "isbn_13": ["9783540719328"], "isbn_10": ["3540719326"], "publish_date": "October 1, 2007", "works": [{"key": "/works/OL14856249W"}]}