{"subtitle": "Jharkhand", "subject_place": ["Jharkhand (India)", "India", "Jharkhand", "Jharkhand."], "lc_classifications": ["RA407.5.I4 K85 2002"], "latest_revision": 3, "contributions": ["Arnold, Fred.", "Roy, T. K.", "International Institute for Population Sciences.", "ORC Macro. MEASURE/DHS+ (Programme)."], "genres": ["Statistics.", "Statistics, Medical."], "source_records": ["marc:marc_records_scriblio_net/part14.dat:68465909:1490", "marc:marc_loc_updates/v37.i04.records.utf8:2055471:1466"], "title": "National family health survey (NFHS-2), India, 1998-99", "languages": [{"key": "/languages/eng"}], "subjects": ["Women -- Health and hygiene -- India -- Jharkhand -- Statistics", "Children -- Health and hygiene -- India -- Jharkhand -- Statistics", "Fertility, Human -- India -- Jharkhand -- Statistics", "Birth control -- India -- Jharkhand -- Statistics", "Health surveys -- India -- Jharkhand", "Demographic surveys -- India -- Jharkhand", "Jharkhand (India) -- Statistics, Medical"], "publish_country": "ii ", "by_statement": "contributors: Sumati Kulkarni, Fred Arnold, T.K. Roy.", "oclc_numbers": ["49213235"], "type": {"key": "/type/edition"}, "revision": 3, "other_titles": ["NFHS-2", "Jharkhand :"], "publishers": ["International Institute for Population Sciences", "MEASURE DHS+, ORC Macro"], "last_modified": {"type": "/type/datetime", "value": "2009-12-12T17:13:16.957193"}, "key": "/books/OL3600221M", "authors": [{"key": "/authors/OL264775A"}], "publish_places": ["Mumbai, India", "Calverton, Md"], "pagination": "vii, 49 p. ;", "created": {"type": "/type/datetime", "value": "2008-04-01T03:28:50.625462"}, "dewey_decimal_class": ["614.4//254/021"], "notes": {"type": "/type/text", "value": "Includes bibliographical references (p. 10).\n\"February 2002\""}, "number_of_pages": 49, "lccn": ["2002328660"], "publish_date": "2002", "works": [{"key": "/works/OL2125007W"}]}