{"subtitle": "with comic illustrations", "series": ["Putnam's popular library"], "lc_classifications": ["PR4797 .U62 1852"], "latest_revision": 5, "source_records": ["marc:marc_records_scriblio_net/part14.dat:15821564:579", "marc:marc_loc_updates/v37.i04.records.utf8:1987028:700", "marc:marc_loc_updates/v40.i30.records.utf8:3379431:700"], "title": "Up the Rhine", "languages": [{"key": "/languages/eng"}], "publish_country": "nyu", "by_statement": "by Thomas Hood.", "type": {"key": "/type/edition"}, "revision": 5, "publishers": ["G.P. Putnam & Co."], "last_modified": {"type": "/type/datetime", "value": "2012-07-25T07:52:17.531636"}, "key": "/books/OL3547286M", "authors": [{"key": "/authors/OL559464A"}], "publish_places": ["New-York"], "pagination": "2 v. :", "created": {"type": "/type/datetime", "value": "2008-04-01T03:28:50.625462"}, "lccn": ["2001553548"], "notes": {"type": "/type/text", "value": "Part 1: 168 p., [1] leaf of plates; Part 2: 173 p., [5] leaves of plates."}, "publish_date": "1852", "works": [{"key": "/works/OL3408878W"}]}