{"subtitle": "told by Ruari Macdonald, redshank and rebel", "subject_place": ["Ireland", "Women pirates"], "lc_classifications": ["PZ3.M1855 G", "PR9199.2 G"], "latest_revision": 3, "subject_time": ["1558-1603"], "genres": ["Fiction."], "source_records": ["marc:marc_records_scriblio_net/part01.dat:184528377:840", "marc:marc_loc_updates/v37.i04.records.utf8:117184:840"], "title": "Grace O'Malley, princess and pirate", "languages": [{"key": "/languages/eng"}], "subjects": ["O'Malley, Grace, 1530?-1603? -- Fiction", "Princesses -- Fiction", "Ireland -- History -- 1558-1603 -- Fiction", "Women pirates -- Fiction"], "publish_country": "nyu", "by_statement": "the same set forth in the tongue of the English, by Robert Machray.", "oclc_numbers": ["12417832"], "type": {"key": "/type/edition"}, "revision": 3, "publishers": ["F.A. Stokes Company"], "last_modified": {"type": "/type/datetime", "value": "2009-12-14T23:38:28.870554"}, "key": "/books/OL6985301M", "authors": [{"key": "/authors/OL120775A"}], "publish_places": ["New York"], "pagination": "vi, 303 p.", "created": {"type": "/type/datetime", "value": "2008-04-01T03:28:50.625462"}, "lccn": ["07019996"], "number_of_pages": 303, "publish_date": "1898", "works": [{"key": "/works/OL1196056W"}]}