{"identifiers": {"librarything": ["4512336"], "goodreads": ["4839468"]}, "subtitle": "Tokyo's grand strategy and the future of East Asia", "series": ["Cornell studies in security affairs", "Cornell paperbacks"], "latest_revision": 7, "source_records": ["marc:marc_loc_updates/v36.i42.records.utf8:19366373:880", "marc:marc_loc_updates/v37.i04.records.utf8:5643815:917", "marc:marc_loc_updates/v37.i25.records.utf8:31839005:951"], "title": "Securing Japan", "languages": [{"key": "/languages/eng"}], "subjects": ["National security -- Japan", "Japan -- Military policy", "Japan -- Foreign relations -- 1945-", "East Asia -- Foreign relations"], "publish_country": "nyu", "by_statement": "Richard J. Samuels.", "oclc_numbers": ["228371888"], "type": {"key": "/type/edition"}, "revision": 7, "publishers": ["Cornell University Press"], "last_modified": {"type": "/type/datetime", "value": "2011-04-25T15:07:49.381736"}, "key": "/books/OL22653591M", "authors": [{"key": "/authors/OL720604A"}], "publish_places": ["Ithaca"], "pagination": "xv, 277 p. :", "created": {"type": "/type/datetime", "value": "2008-12-04T09:58:28.248396"}, "lccn": ["2008276186"], "notes": {"type": "/type/text", "value": "Includes bibliographical references (p. 249-272) and index."}, "number_of_pages": 277, "isbn_13": ["9780801474903"], "publish_date": "2008", "works": [{"key": "/works/OL3950116W"}]}