{"table_of_contents": [{"level": 0, "label": "", "pagenum": "", "title": "The politics of Palestinian legal reform : judicial independence and accountability under occupation / Tobias Kelly"}, {"level": 0, "label": "", "pagenum": "", "title": "Traditional authority and localization of state law : the intricacies of boundary marking in policing rural Mozambique / Helene Maria Kyed"}, {"level": 0, "label": "", "pagenum": "", "title": "The vision of the state : audiences, enchantments and policing in South Africa / Steffen Jensen"}, {"level": 0, "label": "", "pagenum": "", "title": "Translating human rights in the margins : a police-migrant encounter in Johannesburg / Julia Hornberger"}, {"level": 0, "label": "", "pagenum": "", "title": "The special field force and Namibian ex-combatant \"reintegration\" / Lalli Metsola"}, {"level": 0, "label": "", "pagenum": "", "title": "On hangings and the dubious embodiment of statehood in Nigerian prisons / Andrew M. Jefferson"}, {"level": 0, "label": "", "pagenum": "", "title": "Taking the snake out of the basket : Indian prison warders' opposition to human rights reform / Tomas Martin"}, {"level": 0, "label": "", "pagenum": "", "title": "Community policing programmes as police human rights strategies in Costa Rica / Quirine Eijkman"}, {"level": 0, "label": "", "pagenum": "", "title": "Commentary : the piggy-in-the-middle / Mike Brogden."}], "lc_classifications": ["JC571 .S7863 2009"], "latest_revision": 5, "subtitle": "the role of state officials in the south", "contributions": ["Jensen, Steffen.", "Jefferson, Andrew M."], "source_records": ["marc:marc_loc_updates/v36.i35.records.utf8:7893293:1748", "marc:marc_loc_updates/v37.i04.records.utf8:5180228:1753", "marc:marc_loc_updates/v37.i36.records.utf8:17755362:1848", "marc:marc_loc_updates/v37.i50.records.utf8:7444771:1853"], "title": "State violence and human rights", "languages": [{"key": "/languages/eng"}], "subjects": ["Human rights", "Political persecution", "Political violence", "Police -- Complaints against"], "publish_country": "nyu", "by_statement": "edited by Steffen Jensen and Andrew M. Jefferson.", "type": {"key": "/type/edition"}, "revision": 5, "publishers": ["Routledge-Cavendish"], "last_modified": {"type": "/type/datetime", "value": "2010-08-19T05:44:01.822031"}, "key": "/books/OL22501016M", "publish_places": ["New York"], "pagination": "p. cm.", "created": {"type": "/type/datetime", "value": "2008-11-15T13:11:39.953800"}, "dewey_decimal_class": ["323/.044091724"], "notes": {"type": "/type/text", "value": "Includes bibliographical references."}, "identifiers": {"librarything": ["8457690"]}, "isbn_13": ["9780415477727"], "lccn": ["2008036251"], "publish_date": "2009"}