{"table_of_contents": [{"level": 0, "label": "", "pagenum": "", "title": "Digital systems and VLSI"}, {"level": 0, "label": "", "pagenum": "", "title": "Fabrication and devices"}, {"level": 0, "label": "", "pagenum": "", "title": "Logic gates"}, {"level": 0, "label": "", "pagenum": "", "title": "Combinational logic networks"}, {"level": 0, "label": "", "pagenum": "", "title": "Sequential machines"}, {"level": 0, "label": "", "pagenum": "", "title": "Subsystem design"}, {"level": 0, "label": "", "pagenum": "", "title": "Floorplanning"}, {"level": 0, "label": "", "pagenum": "", "title": "Architecture design"}, {"level": 0, "label": "", "pagenum": "", "title": "A chip designer's lexicon"}, {"level": 0, "label": "", "pagenum": "", "title": "Hardware description languages."}], "lc_classifications": ["TK7874.65 .W65 2008"], "latest_revision": 6, "subtitle": "IP-based design", "edition_name": "4th ed.", "source_records": ["marc:marc_loc_updates/v36.i38.records.utf8:13832018:1080", "marc:marc_loc_updates/v37.i04.records.utf8:5267035:1479", "marc:marc_loc_updates/v37.i36.records.utf8:21511421:1566", "marc:marc_loc_updates/v37.i45.records.utf8:4975714:1566"], "title": "Modern VLSI design", "languages": [{"key": "/languages/eng"}], "subjects": ["Digital integrated circuits -- Computer-aided design", "Logic circuits -- Computer-aided design", "Design protection", "Intellectual property"], "publish_country": "nju", "by_statement": "Wayne Wolf.", "type": {"key": "/type/edition"}, "revision": 6, "publishers": ["Prentice Hall"], "last_modified": {"type": "/type/datetime", "value": "2010-04-16T14:15:49.117942"}, "key": "/books/OL22542515M", "authors": [{"key": "/authors/OL224973A"}], "publish_places": ["Upper Saddle River, NJ"], "pagination": "p. cm.", "created": {"type": "/type/datetime", "value": "2008-11-16T00:55:17.348048"}, "dewey_decimal_class": ["621.39/5"], "notes": {"type": "/type/text", "value": "Includes bibliographical references and index."}, "identifiers": {"goodreads": ["6740840"]}, "lccn": ["2008040479"], "isbn_10": ["0137145004"], "publish_date": "2008", "works": [{"key": "/works/OL1879112W"}]}