{"latest_revision": 7, "contributions": ["Ran\u02bbkun\u02bb Takkasuil\u02bb. Ca\u0304 kran\u0303n\u0303\u02bb\u02b9 tuik\u02bb nhan\u0307\u02bb\u02b9 Suta Pan\u0303n\u0303a\u0304 T\u0323ha\u0304na."], "source_records": ["marc:marc_loc_updates/v36.i38.records.utf8:15041484:1116", "marc:marc_loc_updates/v37.i04.records.utf8:6025325:1238", "marc:marc_loc_updates/v36.i42.records.utf8:19800790:1054", "marc:marc_loc_updates/v36.i43.records.utf8:9169497:1056", "marc:marc_loc_updates/v37.i07.records.utf8:5142044:1248", "marc:marc_loc_updates/v37.i42.records.utf8:74962545:1248"], "title": "Ca\u0304 kran\u0303n\u0303\u02bb\u02b9 tuik\u02bb nhan\u0307\u02bb\u02b9 suta Pan\u0303n\u0303a\u0304 Di\u0304paluima\u0304 Bhvai\u02b9 yu\u0304 ca\u0304 tam\u02bb\u02ba mya\u0304\u02ba e* ca\u0304 cu ca\u0304 ran\u0307\u02bb\u02ba \u02bca mhat\u02bb can\u0303\u02bb (1) mha \u02bca mhat\u02bb can\u0303\u02bb (13) \u02bca thi (1971-1999)", "languages": [{"key": "/languages/bur"}], "publish_country": "br ", "by_statement": "Nvai\u02b9 Nvai\u02b9 Ri\u0304, pru cu su\u0304.", "type": {"key": "/type/edition"}, "revision": 7, "publishers": ["Ran\u02bb kun\u02bb Takkasuil\u02bb, Ca\u0304 kran\u0303n\u0303\u02bb\u02b9 tuik\u02bb nhan\u0307\u02bb\u02b9 Suta Pan\u0303n\u0303a\u0304 T\u0323ha\u0304na"], "description": {"type": "/type/text", "value": "Bibliography of thesis papers on Library and Information Science Studies."}, "last_modified": {"type": "/type/datetime", "value": "2009-12-15T07:51:14.502951"}, "key": "/books/OL22544327M", "authors": [{"key": "/authors/OL6473006A"}], "publish_places": ["[Yangon, Burma]"], "pagination": "145 p. :", "created": {"type": "/type/datetime", "value": "2008-11-16T01:24:31.235870"}, "lccn": ["2008320127"], "notes": {"type": "/type/text", "value": "Thesis (Dip. Lib.--Ran\u02bb kun\u02bb Takkasuil\u02bb, 2000).\n\nIncludes bibliographical references (p. [8]) and index.\n\nIn Burmese, with some English."}, "number_of_pages": 145, "publish_date": "2000", "works": [{"key": "/works/OL13614793W"}]}