{"subtitle": "Gemeinde im Kreis Calw in W\u00fcrttemberg,1595-1952", "series": ["Deutsche Ortssippenb\u00fccher. Reihe A -- Bd. 467", "W\u00fcrttembergische Ortssippenb\u00fccher -- Bd. 88"], "lc_classifications": ["CS627.E315 O37 2008"], "latest_revision": 3, "edition_name": "1. Aufl.", "genres": ["Genealogy."], "source_records": ["marc:marc_loc_updates/v37.i01.records.utf8:6598265:849", "marc:marc_loc_updates/v37.i04.records.utf8:8006962:849"], "title": "Ortssippenbuch Egenhausen", "languages": [{"key": "/languages/ger"}], "subjects": ["Registers of births, etc. -- Germany -- Egenhausen (Baden-W\u00fcrttemberg)", "Egenhausen (Baden-W\u00fcrttemberg, Germany) -- Genealogy"], "publish_country": "gw ", "by_statement": "von Burkhart Oertel", "type": {"key": "/type/edition"}, "revision": 3, "publishers": ["B. Oertel"], "last_modified": {"type": "/type/datetime", "value": "2009-12-09T06:06:45.732443"}, "key": "/books/OL22855077M", "authors": [{"key": "/authors/OL75691A"}], "publish_places": ["Neubiberg"], "pagination": "211 p. :", "created": {"type": "/type/datetime", "value": "2009-01-07T22:43:42.604729"}, "lccn": ["2008478189"], "notes": {"type": "/type/text", "value": "includes index."}, "number_of_pages": 211, "publish_date": "2008", "works": [{"key": "/works/OL867565W"}]}