{"number_of_pages": 220, "subject_place": ["Great Britain"], "covers": [4393736], "lc_classifications": ["JA84.G7 M6 1980"], "latest_revision": 7, "source_records": ["marc:marc_records_scriblio_net/part11.dat:98463164:916", "marc:marc_loc_updates/v37.i04.records.utf8:790395:909"], "title": "Political thought in England, Tyndale to Hooker", "languages": [{"key": "/languages/eng"}], "subjects": ["Political science -- Great Britain -- History", "Church and state -- Great Britain -- History"], "publish_country": "ctu", "by_statement": "Christopher Morris.", "type": {"key": "/type/edition"}, "revision": 7, "publishers": ["Hyperion Press"], "last_modified": {"type": "/type/datetime", "value": "2010-08-03T22:32:10.377229"}, "key": "/books/OL4400748M", "authors": [{"key": "/authors/OL1755535A"}], "publish_places": ["Westport, Conn"], "pagination": "x, 220 p. ;", "created": {"type": "/type/datetime", "value": "2008-04-01T03:28:50.625462"}, "dewey_decimal_class": ["320.5/0941"], "notes": {"type": "/type/text", "value": "Bibliography: p. [199]-213.\nReprint of the 1953 ed. published by Oxford University Press, London, New York, in series: Home university library of modern knowledge, 225.\nIncludes index."}, "identifiers": {"librarything": ["789330"], "goodreads": ["2720704"]}, "lccn": ["79001638"], "isbn_10": ["0883559412"], "publish_date": "1980", "works": [{"key": "/works/OL6553234W"}]}