{"bio": "Picasso was a Spanish painter, draughtsman, and sculptor. He is one of the most recognized figures in 20th-century art. Among his most famous works are the proto-Cubist Les Demoiselles d'Avignon (1907) and Guernica (1937), his portrayal of the German bombing of Guernica during the Spanish Civil War.", "name": "Pablo Picasso", "links": [{"url": "http://en.wikipedia.org/wiki/Pablo_Picasso", "type": {"key": "/type/link"}, "title": "Wikipedia entry"}, {"url": "http://www.picasso.fr/us/picasso_page_index.php", "type": {"key": "/type/link"}, "title": "picasso.fr"}], "created": {"type": "/type/datetime", "value": "2008-04-01T03:28:50.625462"}, "death_date": "8 April 1973", "alternate_names": [""], "photos": [6286797], "last_modified": {"type": "/type/datetime", "value": "2010-01-26T00:36:58.960304"}, "latest_revision": 5, "key": "/authors/OL44790A", "birth_date": "25 October 1881", "personal_name": "Pablo Picasso", "type": {"key": "/type/author"}, "id": 111893, "revision": 5}