{"subtitle": "sha\u0304\u02bbiri\u0304", "lc_classifications": ["MLCSA 94/01582 (P)"], "latest_revision": 3, "edition_name": "1. aid\u0323i\u0304shan.", "source_records": ["marc:marc_records_scriblio_net/part24.dat:31594695:808", "marc:marc_loc_updates/v37.i04.records.utf8:1415839:843"], "title": "Su\u0304raju mukhi\u0304\u02bca sa\u0304njh", "languages": [{"key": "/languages/snd"}], "publish_country": "pk ", "by_statement": "Shaik\u0332h\u0332u Aya\u0304zu.", "type": {"key": "/type/edition"}, "revision": 3, "other_titles": ["Sooraj makhi sanjah."], "publishers": ["Niyu\u0304 Fi\u0304ld\u0323s Pabli\u0304keshans"], "last_modified": {"type": "/type/datetime", "value": "2009-12-11T23:39:45.949124"}, "key": "/books/OL1066836M", "authors": [{"key": "/authors/OL101449A"}], "publish_places": ["H\u0323aidara\u0304ba\u0304d Sindh"], "pagination": "350 p. ;", "created": {"type": "/type/datetime", "value": "2008-04-01T03:28:50.625462"}, "lccn": ["93930747"], "notes": {"type": "/type/text", "value": "Poems.\nIn Sindhi.\nTitle on t.p. verso: Sooraj makhi sanjah.\n\"Niyu\u0304 Fi\u0304ld\u0323s Pabli\u0304keshans jo kita\u0304bu nambaru hiku sau\u02bca panjahatar.\"--T.p. verso."}, "number_of_pages": 350, "publish_date": "1993", "works": [{"key": "/works/OL1036867W"}]}