{"number_of_pages": 257, "subtitle": "rediscovering our spiritual roots", "subject_place": ["United States"], "covers": [3858368], "lc_classifications": ["BL2525 .B86 1997"], "latest_revision": 5, "id": 1541583, "subject_time": ["1993-2001."], "source_records": ["marc:marc_records_scriblio_net/part25.dat:198284142:870", "marc:marc_loc_updates/v37.i04.records.utf8:1564502:870"], "title": "Hallowed ground", "languages": [{"key": "/languages/eng"}], "subjects": ["Democracy -- Religious aspects", "United States -- Politics and government -- 1993-2001", "United States -- History -- Religious aspects", "United States -- Moral conditions"], "publish_country": "nyu", "by_statement": "Stephen Burgard ; foreword by Benjamin J. Hubbard.", "type": {"key": "/type/edition"}, "revision": 5, "publishers": ["Insight Books"], "last_modified": {"type": "/type/datetime", "value": "2010-04-15T14:08:00.851191"}, "key": "/books/OL1000542M", "authors": [{"key": "/authors/OL540947A"}], "publish_places": ["New York"], "pagination": "xvii, 257 p. ;", "created": {"type": "/type/datetime", "value": "2008-04-01T03:28:50.625462"}, "dewey_decimal_class": ["291.1/7/0973"], "notes": {"type": "/type/text", "value": "Includes bibliographical references (p. 231-243) and index."}, "identifiers": {"goodreads": ["5132653"]}, "lccn": ["96039457"], "isbn_10": ["0306455684"], "publish_date": "1997", "works": [{"key": "/works/OL3337345W"}]}