{"number_of_pages": 24, "series": ["I'm alive"], "lc_classifications": ["QP84 .S84 1992"], "latest_revision": 5, "contributions": ["Gordon, Mike, ill."], "source_records": ["marc:marc_records_scriblio_net/part22.dat:21856845:874", "marc:marc_loc_updates/v37.i04.records.utf8:1251177:889"], "title": "I am growing", "languages": [{"key": "/languages/eng"}], "subjects": ["Growth -- Juvenile literature", "Children -- Growth -- Juvenile literature", "Growth"], "publish_country": "mnu", "by_statement": "written by Mandy Suhr ; illustrated by Mike Gordon.", "type": {"key": "/type/edition"}, "revision": 5, "publishers": ["Carolrhoda Books"], "description": {"type": "/type/text", "value": "Explains, in easy-to-read text, that we need food, sleep, and exercise to grow."}, "last_modified": {"type": "/type/datetime", "value": "2010-07-31T04:16:06.763120"}, "key": "/books/OL1554712M", "authors": [{"key": "/authors/OL720437A"}], "publish_places": ["Minneapolis"], "pagination": "24 p. :", "created": {"type": "/type/datetime", "value": "2008-04-01T03:28:50.625462"}, "dewey_decimal_class": ["612.6/5"], "identifiers": {"librarything": ["1811361"], "goodreads": ["3146181"]}, "lccn": ["91034840"], "isbn_10": ["0876147341"], "publish_date": "1992", "works": [{"key": "/works/OL3949385W"}]}