{"number_of_pages": 205, "subtitle": "seitaikei o hakaisuru riz\u014dto kaihatsu to n\u014dyakuka", "lc_classifications": ["GV975 T36 1990"], "latest_revision": 4, "source_records": ["marc:marc_loc_updates/v37.i04.records.utf8:1237715:1084"], "title": "Osorubeki gorufuj\u014d osen", "languages": [{"key": "/languages/jpn"}], "subjects": ["Golf courses -- Environmental aspects -- Japan", "Agricultural chemicals -- Environmental aspects -- Japan", "Environmental policy -- Japan"], "publish_country": "ja ", "by_statement": "Taniyama Tetsur\u014d.", "oclc_numbers": ["23838252"], "type": {"key": "/type/edition"}, "revision": 4, "publishers": ["G\u014dd\u014d Shuppan"], "last_modified": {"type": "/type/datetime", "value": "2011-04-28T23:25:46.034095"}, "key": "/books/OL23144930M", "authors": [{"key": "/authors/OL6600234A"}], "publish_places": ["T\u014dky\u014d"], "pagination": "205 p., [6] p. of plates :", "created": {"type": "/type/datetime", "value": "2009-04-27T19:11:18.023669"}, "lccn": ["90224256"], "notes": {"type": "/type/text", "value": "Includes bibliographical references (p. 193-194)."}, "identifiers": {"goodreads": ["4391405"]}, "isbn_10": ["4772601473"], "publish_date": "1990", "works": [{"key": "/works/OL13758235W"}]}