{"lc_classifications": ["QL638.B6 B56 2009"], "latest_revision": 5, "contributions": ["Patzner, Robert A."], "id": 33930240, "source_records": ["marc:marc_loc_updates/v37.i04.records.utf8:9228908:623", "marc:marc_loc_updates/v37.i38.records.utf8:28677348:814", "marc:marc_loc_updates/v37.i47.records.utf8:13354334:907", "marc:marc_loc_updates/v38.i10.records.utf8:8865065:907"], "title": "The biology of blennies", "languages": [{"key": "/languages/eng"}], "subjects": ["Blenniidae"], "publish_country": "nhu", "by_statement": "editors, Robert A. Patzner ... [et al.].", "type": {"key": "/type/edition"}, "revision": 5, "publishers": ["Science Publishers"], "last_modified": {"type": "/type/datetime", "value": "2010-04-16T14:27:44.831519"}, "key": "/books/OL23147970M", "publish_places": ["Enfield, N.H"], "pagination": "p. cm.", "created": {"type": "/type/datetime", "value": "2009-04-27T22:16:49.579160"}, "dewey_decimal_class": ["597/.77"], "notes": {"type": "/type/text", "value": "Includes bibliographical references and index."}, "identifiers": {"goodreads": ["6797738"]}, "isbn_13": ["9781578084395"], "lccn": ["2009002035"], "publish_date": "2009"}