{"subtitle": "anatomi Undang-Undang no. 25 tahun 2007 Tentang Penanaman Modal", "lc_classifications": ["KNW3202 .R346 2007"], "latest_revision": 3, "contributions": ["Indonesia."], "source_records": ["marc:marc_loc_updates/v37.i04.records.utf8:4156984:1053"], "title": "Hukum investasi di Indonesia", "languages": [{"key": "/languages/ind"}], "subjects": ["Investments, Foreign -- Law and legislation -- Indonesia", "Investments -- Law and legislation -- Indonesia", "Capital investments -- Law and legislation -- Indonesia"], "publish_country": "io ", "by_statement": "Erman Rajagukguk.", "oclc_numbers": ["185021850"], "type": {"key": "/type/edition"}, "revision": 3, "publishers": ["Universitas Al-Azhar Indonesia"], "description": {"type": "/type/text", "value": "Comments on law on investment in Indonesia."}, "last_modified": {"type": "/type/datetime", "value": "2011-04-27T09:22:33.242043"}, "key": "/books/OL23145555M", "authors": [{"key": "/authors/OL84126A"}], "publish_places": ["[Jakarta]"], "pagination": "vi, 301 p. ;", "created": {"type": "/type/datetime", "value": "2009-04-27T20:24:46.683162"}, "lccn": ["2007448024"], "notes": {"type": "/type/text", "value": "Includes the text of: Undang-Undang Tentang Penanaman Modal.\n\nIncludes bibliographical references."}, "number_of_pages": 301, "isbn_13": ["9789799798015"], "publish_date": "2007", "works": [{"key": "/works/OL945946W"}]}