{"number_of_pages": 127, "series": ["Images of America"], "lc_classifications": ["F869.R412 R32 2008"], "latest_revision": 4, "contributions": ["McGovern, Reg."], "genres": ["Pictorial works."], "source_records": ["marc:marc_loc_updates/v37.i06.records.utf8:11706947:711", "marc:marc_loc_updates/v37.i04.records.utf8:8594886:682"], "title": "Redwood City", "languages": [{"key": "/languages/eng"}], "subjects": ["Redwood City (Calif.) -- History -- Pictorial works", "Redwood City (Calif.) -- Social life and customs -- Pictorial works"], "publish_country": "scu", "by_statement": "Reg McGovern ... [et al.].", "oclc_numbers": ["263093808"], "type": {"key": "/type/edition"}, "revision": 4, "publishers": ["Arcadia Pub."], "last_modified": {"type": "/type/datetime", "value": "2011-04-26T21:26:12.513642"}, "key": "/books/OL23053285M", "publish_places": ["Charleston, S.C"], "pagination": "127 p. :", "created": {"type": "/type/datetime", "value": "2009-02-18T06:53:31.860326"}, "dewey_decimal_class": ["979.4/69"], "identifiers": {"goodreads": ["5755513"]}, "isbn_13": ["9780738559247"], "lccn": ["2008928307"], "publish_date": "2008"}