{"lc_classifications": ["PK1852 (P-PZ24)+"], "latest_revision": 2, "contributions": ["Brahmabha\u1e6d\u1e6da, Bhag\u012bratha."], "id": 33927633, "languages": [{"key": "/languages/guj"}], "source_records": ["marc:marc_loc_updates/v37.i04.records.utf8:6114396:970", "marc:marc_loc_updates/v37.i18.records.utf8:7265239:971"], "title": "Madhyak\u0101l\u012bna Gujar\u0101t\u012b kavit\u0101no vaibhava", "edition_name": "1. \u0101vr\u0325tti.", "subjects": ["Gujarati poetry -- 1500-1800 -- History and criticism", "Gujarati poetry -- 1500-1800"], "publish_country": "ii ", "by_statement": "samp\u0101daka Bhag\u012bratha Brahmabha\u1e6d\u1e6da.", "type": {"key": "/type/edition"}, "revision": 2, "other_titles": ["Madhyakalin Gujarati kavitano vaibhav"], "publishers": ["Rann\u0101de Prak\u0101\u015bana"], "description": {"type": "/type/text", "value": "Study of 50 medieval Gujarati poems; includes text also."}, "last_modified": {"type": "/type/datetime", "value": "2009-05-16T09:44:02.377743"}, "key": "/books/OL23146021M", "publish_places": ["Amad\u0101v\u0101da"], "pagination": "70 p. ;", "created": {"type": "/type/datetime", "value": "2009-04-27T21:08:01.766726"}, "lccn": ["2008324864"], "notes": {"type": "/type/text", "value": "In Gujarati."}, "number_of_pages": 70, "publish_date": "2008"}