{"subtitle": "una visi\u00f3n de Naciones Unidas y la Banca Multilateral.", "series": ["Gesti\u00f3n del desarrollo con identidad -- 1"], "lc_classifications": ["KHC2202 .P84 2007"], "latest_revision": 1, "contributions": ["Fondo para el Desarrollo de los Pueblos Ind\u00edgenas de Am\u00e9rica Latina y El Caribe."], "id": 33928758, "source_records": ["marc:marc_loc_updates/v37.i04.records.utf8:7735587:1025"], "title": "Pueblos ind\u00edgenas", "languages": [{"key": "/languages/spa"}], "subjects": ["Indigenous peoples -- Legal status, laws, etc. -- Bolivia"], "publish_country": "bo ", "type": {"key": "/type/edition"}, "revision": 1, "publishers": ["Fondo Ind\u00edgena", "Secretar\u00eda T\u00e9cnica, Comisi\u00f3n de Desarrollo con Identidad"], "last_modified": {"type": "/type/datetime", "value": "2009-04-27T21:42:35.721244"}, "key": "/books/OL23146838M", "publish_places": ["La Paz, Bolivia"], "pagination": "182 p. ;", "created": {"type": "/type/datetime", "value": "2009-04-27T21:42:35.721244"}, "lccn": ["2008462518"], "notes": {"type": "/type/text", "value": "\"Pronunciamientos, propuestas y debate sobre desarrollo ind\u00edgena y el \"derecho al desarrollo\" en la ONU y en los organismos financieros internacionales.\"\n\nIncludes bibliographical references (p. 167-182)."}, "number_of_pages": 182, "publish_date": "2007"}