{"publishers": ["New Patriotic Party"], "pagination": "31 p. :", "subtitle": "date, August 15-17, 2008 : venue, Sekondi College.", "source_records": ["marc:marc_loc_updates/v37.i04.records.utf8:6464840:700", "marc:marc_loc_updates/v37.i13.records.utf8:9024778:700", "marc:marc_loc_updates/v37.i18.records.utf8:7522002:873"], "title": "New Patriotic Party Annual Delegates Conference, 2008", "lccn": ["2008345750"], "contributions": ["New Patriotic Party (Ghana)"], "notes": {"type": "/type/text", "value": "Cover title.\n\n\"Official magazine.\"\n\n\"Theme, We are moving forward.\""}, "number_of_pages": 31, "created": {"type": "/type/datetime", "value": "2009-04-27T21:15:19.719520"}, "languages": [{"key": "/languages/eng"}], "last_modified": {"type": "/type/datetime", "value": "2009-12-15T08:25:51.718882"}, "latest_revision": 4, "publish_country": "gh ", "key": "/books/OL23146208M", "authors": [{"key": "/authors/OL6600675A"}], "publish_date": "2008", "publish_places": ["[Accra"], "works": [{"key": "/works/OL13758702W"}], "type": {"key": "/type/edition"}, "revision": 4}