{"publishers": ["Ghir\u0101s lil-Nashr wa-al-Tawz\u012b\u02bb wa-al-di\u02bb\u0101yah wa-al-I\u02bbl\u0101n"], "pagination": "343 p. ;", "description": {"type": "/type/text", "value": "Islamic education; Islam; doctrines."}, "source_records": ["marc:marc_loc_updates/v37.i04.records.utf8:9739378:1378", "marc:marc_loc_updates/v37.i13.records.utf8:12902314:1724", "marc:marc_loc_updates/v37.i18.records.utf8:11408740:1725", "marc:marc_loc_updates/v38.i16.records.utf8:12553370:1682"], "title": "al-I\u1e63b\u0101\u1e25 f\u012b bay\u0101n manhaj al-salaf f\u012b al-tarbiyah wa-al-i\u1e63l\u0101\u1e25", "lccn": ["2009338142"], "number_of_pages": 343, "created": {"type": "/type/datetime", "value": "2009-04-27T22:30:20.492284"}, "languages": [{"key": "/languages/ara"}], "last_modified": {"type": "/type/datetime", "value": "2010-11-24T03:44:41.444503"}, "latest_revision": 5, "edition_name": "880-03 al-\u1e6cab\u02bbah 1.", "key": "/books/OL23148407M", "authors": [{"key": "/authors/OL6601310A"}], "revision": 5, "publish_date": "2008", "publish_places": ["al-Kuwayt"], "works": [{"key": "/works/OL13759374W"}], "type": {"key": "/type/edition"}, "by_statement": "raja\u02bbahu wa-\u1e63a\u1e25\u1e25a\u1e25ahu wa-qaddama la-hu wa-\u02bballaqa \u02bbalayh \u1e62\u0101li\u1e25 ibn Fawz\u0101n al-Fawz\u0101n ; bi-qalam \u02bbAbd All\u0101h ibn \u1e62\u0101li\u1e25 al-\u02bbUbayl\u0101n,.", "publish_country": "ku "}