{"lc_classifications": ["H61.4 .M35 2007"], "latest_revision": 1, "contributions": ["Bestuzhev-Lada, Igor\u02b9 Vasil\u02b9evich."], "id": 33928886, "genres": ["Encyclopedias"], "source_records": ["marc:marc_loc_updates/v37.i04.records.utf8:7830755:787"], "title": "Malai\ufe20a\ufe21 rossi\u012dskai\ufe20a\ufe21 \u0117nt\ufe20s\ufe21iklopedii\ufe20a\ufe21 prognostiki", "languages": [{"key": "/languages/rus"}], "subjects": ["Social prediction -- Encyclopedias", "Technological forecasting -- Encyclopedias", "Forecasting -- Encyclopedias"], "publish_country": "ru ", "by_statement": "redaktsionnaia kollegii\ufe20a\ufe21, I.V. Bestuzhev-Lada (gl. redaktor) ... et al.", "type": {"key": "/type/edition"}, "revision": 1, "publishers": ["In-tut \u0117konomicheskikh strategi\u012d"], "last_modified": {"type": "/type/datetime", "value": "2009-04-27T21:44:52.078522"}, "key": "/books/OL23146926M", "publish_places": ["Moskva"], "pagination": "326 p. :", "created": {"type": "/type/datetime", "value": "2009-04-27T21:44:52.078522"}, "lccn": ["2008467957"], "number_of_pages": 326, "isbn_10": ["5936181251"], "publish_date": "2007"}