{"series": ["Global issues"], "lc_classifications": ["QC981.8.G56 J35 2010"], "latest_revision": 3, "genres": ["Juvenile literature"], "source_records": ["marc:marc_loc_updates/v37.i04.records.utf8:9223180:613", "marc:marc_loc_updates/v38.i38.records.utf8:5210862:1051"], "title": "Global warming", "languages": [{"key": "/languages/eng"}], "subjects": ["Global warming -- Juvenile literature"], "publish_country": "mnu", "by_statement": "Cheryl Jakab.", "type": {"key": "/type/edition"}, "revision": 3, "publishers": ["Smart Apple Media"], "last_modified": {"type": "/type/datetime", "value": "2010-10-20T01:16:19.005546"}, "key": "/books/OL23147964M", "authors": [{"key": "/authors/OL1436654A"}], "publish_places": ["Mankato, Minn"], "pagination": "p. cm.", "created": {"type": "/type/datetime", "value": "2009-04-27T22:16:44.618648"}, "dewey_decimal_class": ["363.738/74"], "notes": {"type": "/type/text", "value": "Includes index."}, "isbn_13": ["9781599204512"], "lccn": ["2009002020"], "publish_date": "2010", "works": [{"key": "/works/OL5852847W"}]}