{"lc_classifications": ["TD171.5.S472 D86 2005"], "latest_revision": 3, "contributions": ["Nagy, Imre."], "source_records": ["marc:marc_loc_updates/v37.i04.records.utf8:4032430:792"], "title": "A vajdas\u00e1gi v\u00e1rosok k\u00f6rnyezet-eg\u00e9szs\u00e9g\u00fcgyi \u00e9rt\u00e9kel\u00e9se az ezredfordul\u00f3n", "languages": [{"key": "/languages/hun"}], "subjects": ["Environmental protection -- Serbia -- Vojvodina"], "publish_country": "hu ", "by_statement": "Dujmovics Ferenc, Nagy Imre.", "oclc_numbers": ["165965407"], "type": {"key": "/type/edition"}, "revision": 3, "publishers": ["MTA RRK Alf\u00f6ldi Tudom\u00e1nyos Int\u00e9zete"], "last_modified": {"type": "/type/datetime", "value": "2011-04-28T18:22:03.818802"}, "key": "/books/OL23145501M", "authors": [{"key": "/authors/OL6600427A"}], "publish_places": ["B\u00e9k\u00e9scsaba"], "pagination": "159 p. :", "created": {"type": "/type/datetime", "value": "2009-04-27T20:22:08.379715"}, "lccn": ["2007422314"], "notes": {"type": "/type/text", "value": "Includes bibliographical references (p. 150-153)."}, "number_of_pages": 159, "isbn_10": ["9632189949"], "publish_date": "2005", "works": [{"key": "/works/OL13758461W"}]}