{"identifiers": {"goodreads": ["6787397"]}, "subtitle": "a tale of literary Edinburgh, 1950-1985", "lc_classifications": ["PR6057.R357 Z54 2007"], "latest_revision": 5, "genres": ["Biography"], "source_records": ["marc:marc_loc_updates/v37.i04.records.utf8:7309042:814"], "title": "A clamjamfray of poets", "languages": [{"key": "/languages/eng"}], "subjects": ["Green, Stanley Roger -- Friends and associates", "Poets, Scottish -- 20th century -- Biography", "Edinburgh (Scotland) -- Intellectual life -- 20th century"], "publish_country": "stk", "by_statement": "Stanley Roger Green.", "oclc_numbers": ["244743787"], "type": {"key": "/type/edition"}, "revision": 5, "publishers": ["The Saltire Society"], "last_modified": {"type": "/type/datetime", "value": "2011-04-28T11:34:18.769091"}, "key": "/books/OL23146578M", "authors": [{"key": "/authors/OL63711A"}], "publish_places": ["Edinburgh"], "pagination": "138 p. ;", "created": {"type": "/type/datetime", "value": "2009-04-27T21:33:00.786523"}, "lccn": ["2008425513"], "notes": {"type": "/type/text", "value": "Includes bibliographical references."}, "number_of_pages": 138, "isbn_13": ["9780854110988"], "isbn_10": ["0854110984"], "publish_date": "2007", "works": [{"key": "/works/OL771242W"}]}