{"series": ["Sports for sprouts"], "lc_classifications": ["GV867.5 .K37 2009"], "latest_revision": 5, "ocaid": "baseball00kara", "genres": ["Juvenile literature"], "source_records": ["marc:marc_loc_updates/v37.i04.records.utf8:9311527:560", "marc:marc_loc_updates/v37.i43.records.utf8:40085245:589"], "title": "Baseball", "languages": [{"key": "/languages/eng"}], "subjects": ["Baseball -- Juvenile literature"], "publish_country": "flu", "by_statement": "Holly Karapetkova.", "oclc_numbers": ["299281575"], "type": {"key": "/type/edition"}, "revision": 5, "publishers": ["Rourke Pub."], "last_modified": {"type": "/type/datetime", "value": "2014-04-06T03:39:15.193584"}, "key": "/books/OL23148047M", "authors": [{"key": "/authors/OL3906852A"}], "publish_places": ["Vero Beach, FL"], "pagination": "p. cm.", "created": {"type": "/type/datetime", "value": "2009-04-27T22:18:35.002687"}, "dewey_decimal_class": ["796.357"], "isbn_13": ["9781606943212"], "lccn": ["2009002253"], "publish_date": "2009", "works": [{"key": "/works/OL9937525W"}]}