{"lc_classifications": ["PK6561.A38 Z55 2007"], "latest_revision": 5, "edition_name": "880-03 Ch\u0101p-i 1.", "source_records": ["marc:marc_loc_updates/v37.i04.records.utf8:5895006:1402", "marc:marc_loc_updates/v37.i11.records.utf8:12963056:1502", "marc:marc_loc_updates/v37.i26.records.utf8:50305666:1502"], "title": "Jal\u0101l \u0100l A\u1e25mad dar \u0101y\u012bnah-i zam\u0101n", "languages": [{"key": "/languages/per"}], "subjects": ["\u0100l A\u1e25mad, Jal\u0101l -- Criticism and interpretation", "\u0100l A\u1e25mad, Jal\u0101l -- Political and social views", "Iran -- History -- Revolution, 1979"], "publish_country": "ir ", "by_statement": "ta\u02bcl\u012bf-i, \u1e62idd\u012bqah Akbar\u012b.", "oclc_numbers": ["299379014"], "type": {"key": "/type/edition"}, "revision": 5, "other_titles": ["Jalal Al-Ahmad and Islamic revolution"], "publishers": ["V\u0101zhah\u02b9\u0101r\u0101"], "last_modified": {"type": "/type/datetime", "value": "2011-04-29T21:45:37.092373"}, "key": "/books/OL23145908M", "authors": [{"key": "/authors/OL6600536A"}], "publish_places": ["Tihr\u0101n"], "pagination": "198 p. ;", "created": {"type": "/type/datetime", "value": "2009-04-27T21:03:04.445304"}, "lccn": ["2008310204"], "notes": {"type": "/type/text", "value": "Includes bibliographical references (p. 191-195).\n\nIn Persian; abstract in English."}, "number_of_pages": 198, "isbn_13": ["9789646498815"], "publish_date": "2007", "works": [{"key": "/works/OL13758564W"}]}