{"subtitle": "Denkphilosophie, Welt- und Menschenbilder in China", "lc_classifications": ["DS721 .H71196 2008"], "latest_revision": 3, "edition_name": "1. Aufl.", "source_records": ["marc:marc_loc_updates/v37.i06.records.utf8:10621872:1202", "marc:marc_loc_updates/v37.i04.records.utf8:7841109:1197"], "title": "Wie Chinesen denken", "languages": [{"key": "/languages/ger"}], "subjects": ["Social psychology -- China", "Interpersonal communication -- China", "China -- Intellectual life", "China -- Intellectual life -- Psychological aspects"], "publish_country": "gw ", "by_statement": "von Ning Huang.", "type": {"key": "/type/edition"}, "revision": 3, "publishers": ["Oldenbourg"], "last_modified": {"type": "/type/datetime", "value": "2009-12-15T08:18:15.427177"}, "key": "/books/OL23049112M", "authors": [{"key": "/authors/OL4663254A"}], "publish_places": ["M\u00fcnchen"], "oclc_number": ["254636879"], "pagination": "xi, 103 p. :", "created": {"type": "/type/datetime", "value": "2009-02-18T06:02:01.890620"}, "lccn": ["2008468479"], "notes": {"type": "/type/text", "value": "Includes bibliographical references (p. [97]-102)."}, "number_of_pages": 103, "isbn_13": ["9783486588149"], "url": ["http://deposit.d-nb.de/cgi-bin/dokserv?id=3131356&prov=M&dok_var=1&dok_ext=htm"], "isbn_10": ["3486588141"], "publish_date": "2008", "works": [{"key": "/works/OL11168289W"}]}