{"publishers": ["Minerals Commission/GTZ Publication Project"], "pagination": "v. <2> :", "source_records": ["marc:marc_loc_updates/v36.i26.records.utf8:11807113:613", "marc:marc_loc_updates/v37.i04.records.utf8:6568404:613", "marc:marc_loc_updates/v37.i03.records.utf8:6771414:613", "marc:marc_loc_updates/v37.i09.records.utf8:6990066:710", "marc:marc_loc_updates/v37.i13.records.utf8:9071315:737"], "title": "Field and progress reports of T. Hirst for the period 1934-1944.", "lccn": ["2008349677"], "series": ["Archive report / Ghana Geological Survey Department -- no. 9"], "notes": {"type": "/type/text", "value": "Description based on: v. 2, published in 1991."}, "created": {"type": "/type/datetime", "value": "2008-09-26T19:00:10.048953"}, "languages": [{"key": "/languages/eng"}], "last_modified": {"type": "/type/datetime", "value": "2009-12-15T03:49:52.228135"}, "latest_revision": 6, "publish_country": "gh ", "key": "/books/OL16947254M", "authors": [{"key": "/authors/OL5165059A"}], "publish_places": ["Accra, Ghana"], "works": [{"key": "/works/OL11984693W"}], "type": {"key": "/type/edition"}, "revision": 6}