{"publishers": ["Charlesbridge"], "pagination": "p. cm.", "languages": [{"key": "/languages/eng"}], "source_records": ["marc:marc_loc_updates/v36.i15.records.utf8:9918175:542", "marc:marc_loc_updates/v37.i04.records.utf8:4502132:602", "marc:marc_loc_updates/v36.i16.records.utf8:11345488:595", "marc:marc_loc_updates/v36.i22.records.utf8:7315679:600", "marc:marc_loc_updates/v36.i24.records.utf8:9607974:600", "marc:marc_loc_updates/v36.i25.records.utf8:13644487:602", "marc:marc_loc_updates/v36.i37.records.utf8:13047441:602", "marc:marc_loc_updates/v39.i49.records.utf8:4793993:618", "marc:marc_loc_updates/v40.i17.records.utf8:2648967:618"], "title": "Under the mambo moon", "lccn": ["2008007255"], "type": {"key": "/type/edition"}, "created": {"type": "/type/datetime", "value": "2008-09-26T00:12:39.686176"}, "by_statement": "Julia Durango ; illustrated by Fabricio VandenBroeck.", "isbn_13": ["9781570917233"], "last_modified": {"type": "/type/datetime", "value": "2012-04-25T06:38:33.882159"}, "latest_revision": 11, "publish_country": "mau", "key": "/books/OL16773600M", "authors": [{"key": "/authors/OL4999504A"}], "publish_date": "2009", "publish_places": ["Watertown, MA"], "works": [{"key": "/works/OL11755300W"}], "contributions": ["Vandenbroeck, Fabricio, 1954-"], "oclc_numbers": ["224440543"], "revision": 11}