{"bio": "Ngawang Lobsang Gyatso (\u0f56\u0fb3\u0f7c\u0f0b\u0f56\u0f5f\u0f44\u0f0b\u0f62\u0f92\u0fb1\u0f0b\u0f58\u0f5a\u0f7c\u0f0b blo bzang rgya mtsho), the 5th Dalai Lama", "name": "5th Dalai Lama", "created": {"type": "/type/datetime", "value": "2008-04-01T03:28:50.625462"}, "death_date": "1682", "alternate_names": ["Ngawang Lobsang Gyatso", "Lobzang Gyatso", "Lopsang Gyatso", "V. Dalai Lama", "V Dalai Lama", "Fifth Dalai Lama", "Nag-dban-blo-bzan-rgya-mtsho Dalai Lama V", "Ngag-dbang bLo-bzang Dalai-lama", "N\u0307ag-dban-blo-bzan\u0307-rgya-mtsho Dalai Lama V", "\u1e44ag-dba\u01f9-blo-bza\u1e45-rgya-mtsho Dalai Lama V", "Dalai Lama V Nag-dba\u1e45-blo-bzan-rgya-mtsho", "Dalai Lama V \u1e44ag-dba\u1e45-blo-bza\u1e45-rgya-mtsho", "\u1e44ag-dba\u1e45-blo-bza\u1e45-rgya-mtsho Dalai Lama V"], "photos": [6462416], "last_modified": {"type": "/type/datetime", "value": "2011-11-15T19:13:08.731461"}, "latest_revision": 7, "key": "/authors/OL16898A", "birth_date": "1617", "title": "Dalai Lama V", "personal_name": "\u1e44ag-dba\u1e45-blo-bza\u1e45-rgya-mtsho", "type": {"key": "/type/author"}, "revision": 7}