{"number_of_pages": 211, "table_of_contents": [{"title": "Moni the goat boy", "type": {"key": "/type/toc_item"}, "level": 0}, {"title": "Without a friend", "type": {"key": "/type/toc_item"}, "level": 0}, {"title": "The little runaway.", "type": {"key": "/type/toc_item"}, "level": 0}], "subject_place": ["Switzerland"], "lc_classifications": ["PZ7.S772 Mo 1993"], "latest_revision": 11, "contributions": ["Kunz, Edith F."], "source_records": ["marc:marc_records_scriblio_net/part23.dat:178105205:985", "marc:marc_loc_updates/v37.i04.records.utf8:1394822:1040"], "title": "Moni the goat boy and other stories", "languages": [{"key": "/languages/eng"}], "subjects": ["Children's stories, Swiss (German)", "Mountain life -- Switzerland -- Fiction", "Switzerland -- Fiction", "Short stories"], "publish_country": "mdu", "by_statement": "translated from the German of Johanna Spyri, author of \"Heidi\", by Edith F. Kunz.", "oclc_numbers": ["29675874"], "type": {"key": "/type/edition"}, "revision": 11, "other_titles": ["Without a friend.", "Little runaway."], "publishers": ["Deutsche Buchhandlung/J. Lowry"], "last_modified": {"type": "/type/datetime", "value": "2014-03-04T00:13:28.637316"}, "key": "/books/OL1489889M", "publish_places": ["Hagerstown, Md"], "pagination": "viii, 211 p. :", "created": {"type": "/type/datetime", "value": "2008-04-01T03:28:50.625462"}, "dewey_decimal_class": ["[Fic]"], "identifiers": {"goodreads": ["3257037"]}, "lccn": ["93161641"], "isbn_10": ["1883453003"], "publish_date": "1993", "works": [{"key": "/works/OL1455038W"}]}