{"lc_classifications": ["TJ217 .A67 2008"], "latest_revision": 5, "contributions": ["Wittenmark, Bjo\u0308rn."], "languages": [{"key": "/languages/eng"}], "source_records": ["marc:marc_loc_updates/v36.i08.records.utf8:13653030:660", "marc:marc_loc_updates/v37.i04.records.utf8:4509051:1046"], "title": "Adaptive control", "edition_name": "2nd ed.", "subjects": ["Adaptive control systems"], "publish_country": "nyu", "by_statement": "Karl J. Astrom and Bjorn Wittenmark.", "type": {"key": "/type/edition"}, "revision": 5, "publishers": ["Dover Publications"], "last_modified": {"type": "/type/datetime", "value": "2010-04-24T19:18:30.823656"}, "key": "/books/OL19970704M", "authors": [{"key": "/authors/OL539904A"}], "publish_places": ["Mineola, N.Y"], "pagination": "p. cm.", "created": {"type": "/type/datetime", "value": "2008-10-25T02:37:39.040243"}, "dewey_decimal_class": ["629.8/36"], "identifiers": {"goodreads": ["3507066"]}, "isbn_13": ["9780486462783"], "lccn": ["2008007690"], "isbn_10": ["0486462781"], "publish_date": "2008", "works": [{"key": "/works/OL3332633W"}]}