{"identifiers": {"librarything": ["400467"], "goodreads": ["1387057"]}, "subtitle": "Schoenberg, Webern, Berg", "subject_place": ["Austria", "Vienna"], "covers": [4044826], "lc_classifications": ["ML390 .N345 1983"], "latest_revision": 7, "contributions": ["Griffiths, Paul, 1947 Nov. 24-", "Perle, George, 1915-"], "edition_name": "1st American ed.", "genres": ["Biography."], "source_records": ["marc:marc_records_scriblio_net/part21.dat:131037722:986", "marc:marc_loc_updates/v37.i04.records.utf8:1228026:991", "marc:marc_loc_updates/v39.i47.records.utf8:1438041:998"], "title": "The New Grove Second Viennese school", "languages": [{"key": "/languages/eng"}], "subjects": ["Composers -- Austria -- Vienna -- Biography", "Second Viennese school (Group of composers)"], "publish_country": "nyu", "series": ["The Composer biography series"], "by_statement": "Oliver Neighbour, Paul Griffiths, George Perle.", "type": {"key": "/type/edition"}, "revision": 7, "other_titles": ["Second Viennese school."], "publishers": ["Norton"], "last_modified": {"type": "/type/datetime", "value": "2011-11-23T07:10:11.530082"}, "key": "/books/OL1934292M", "authors": [{"key": "/authors/OL912023A"}], "publish_places": ["New York"], "pagination": "201 p. :", "created": {"type": "/type/datetime", "value": "2008-04-01T03:28:50.625462"}, "dewey_decimal_class": ["780/.92/2436", "B"], "notes": {"type": "/type/text", "value": "Includes bibliographical references and index."}, "number_of_pages": 201, "lccn": ["90151386"], "isbn_10": ["0393016862"], "publish_date": "1983", "works": [{"key": "/works/OL4532474W"}]}