{"table_of_contents": [{"type": {"key": "/type/toc_item"}, "title": "Like a stab in the back / John M. Littrell"}, {"type": {"key": "/type/toc_item"}, "title": "Cystic fibrosis, alcoholism, and meaning / Thelma Duffey"}, {"type": {"key": "/type/toc_item"}, "title": "Help! she's old and I'm young but she's 57 and I'm 65 / Marijane Fall"}, {"type": {"key": "/type/toc_item"}, "title": "The \"transition\" experience : group counseling for baby boomers / Mary Finn Maples"}, {"type": {"key": "/type/toc_item"}, "title": "The existential issues of freedom and responsibility : every year it is getting harder to deny them! / Collie W. Conoley and Jane Close Conoley"}, {"type": {"key": "/type/toc_item"}, "title": "Sandtray and artwork : the woman who created herself / Beverly Snyder"}, {"type": {"key": "/type/toc_item"}, "title": "Life losses and changes from a transactional analysis perspective / Susan A. Adams"}, {"type": {"key": "/type/toc_item"}, "title": "Counseling Flora : adjusting, grieving, dating, and moving on / Fred Stickle and Jill Duba Onedera"}, {"type": {"key": "/type/toc_item"}, "title": "The second time around / Heather Trepal"}, {"type": {"key": "/type/toc_item"}, "title": "Existential crisis and the loss of a spouse / Montserrat Casado-Kehoe"}, {"type": {"key": "/type/toc_item"}, "title": "An absence of light : the case of Marie / Catherine B. Roland"}, {"type": {"key": "/type/toc_item"}, "title": "Living with dying : alcohol is not the answer / Mary B. Ballard, Hunter Alessi, and June M. Williams"}, {"type": {"key": "/type/toc_item"}, "title": "I don't know if this therapy is helping me / Ana Blancarte"}, {"type": {"key": "/type/toc_item"}, "title": "Catherine's story : challenges of aging in a rural community / Dorothy Breen"}, {"type": {"key": "/type/toc_item"}, "title": "Mama Del : a case study of counseling in post-Katrina New Orleans / Barbara J. Herlihy and Zarus E. Watson"}, {"type": {"key": "/type/toc_item"}, "title": "Dad just fell again : out of AA and into grief / Peggy P. Whiting and Loretta J. Bradley"}, {"type": {"key": "/type/toc_item"}, "title": "\"Tired of living\" or \"all packed and ready to go?\" / Suzanne E. Degges-White"}, {"type": {"key": "/type/toc_item"}, "title": "The music of memory / Bret Hendricks and Loretta J. Bradley."}], "lc_classifications": ["HV1451 .C37 2009"], "latest_revision": 3, "contributions": ["Golden, Larry B."], "id": 31248504, "languages": [{"key": "/languages/eng"}], "genres": ["Case studies.", "Case Reports."], "source_records": ["marc:marc_loc_updates/v36.i22.records.utf8:7876685:2401", "marc:marc_loc_updates/v37.i04.records.utf8:4806371:2432", "marc:marc_loc_updates/v37.i35.records.utf8:57968376:2527"], "title": "Case studies in counseling older adults", "edition_name": "1st ed.", "subjects": ["Older people -- Counseling of -- Case studies", "Mental Disorders -- therapy -- Case Reports", "Aged", "Middle Aged", "Psychotherapy -- methods -- Case Reports"], "publish_country": "mau", "by_statement": "[edited by] Larry B. Golden.", "type": {"key": "/type/edition"}, "revision": 3, "publishers": ["Pearson Education"], "last_modified": {"type": "/type/datetime", "value": "2009-09-04T07:06:14.431372"}, "key": "/books/OL20988598M", "publish_places": ["Boston"], "pagination": "p. ;", "created": {"type": "/type/datetime", "value": "2008-10-31T09:05:04.689100"}, "dewey_decimal_class": ["362.6/6"], "notes": {"type": "/type/text", "value": "Includes bibliographical references and index."}, "isbn_13": ["9780132232623"], "lccn": ["2008021794"], "isbn_10": ["0132232626"], "publish_date": "2009"}